[
    {
        "id": 7,
        "location": "Blue Back Square, West Hartford, Connecticut",
        "date": "July 29, 2020",
        "filename": "P030.jpg",
        "thumbnail": "P030 Resized.jpg",
        "post": "8"
    },
    {
        "id": 6,
        "location": "Blue Back Square, West Hartford, Connecticut",
        "date": "July 28, 2020",
        "filename": "P019.jpg",
        "thumbnail": "P019 Resized.jpg",
        "post": "7"
    },
    {
        "id": 5,
        "location": "Blue Back Square, West Hartford, Connecticut",
        "date": "July 27, 2020",
        "filename": "P027.jpg",
        "thumbnail": "P027 Resized.jpg",
        "post": "6"
    },
    {
        "id": 4,
        "location": "Blue Back Square, West Hartford, Connecticut",
        "date": "July 23, 2020",
        "filename": "P020.jpg",
        "thumbnail": "P020 Resized.jpg",
        "post": "5"
    },
    {
        "id": 3,
        "location": "Blue Back Square, West Hartford, Connecticut",
        "date": "July 22, 2020",
        "filename": "P018.jpg",
        "thumbnail": "P018 Resized.jpg",
        "post": "4"
    },
    {
        "id": 2,
        "location": "Blue Back Square, West Hartford, Connecticut",
        "date": "July 21, 2020",
        "filename": "P016.jpg",
        "thumbnail": "P016 Resized.jpg",
        "post": "3"
    },
    {
        "id": 1,
        "caption": "When it rains, it pours.",
        "location": "Hartford, Connecticut",
        "date": "May 9, 2020",
        "products": "Uniqlo Blocktech Fishtail Parka and Casio DW5600BB",
        "credit": "",
        "filename": "011.jpg",
        "thumbnail": "011 Resized.jpg",
        "post": "2"
    },
    {
        "id": 0,
        "caption": "Selectively social.",
        "location": "Hartford, Connecticut",
        "date": "May 5, 2020",
        "products": "PSNY X Alpha Industies MA-1 and Seiko SKX009",
        "credit": "",
        "filename": "009.jpg",
        "thumbnail": "009 Resized.jpg",
        "post": "1"
    }
]